LeEncoderML
