Metadata-Version: 2.1
Name: LeEncoderML
Version: 0.1.0
Summary: Python script for managing categorical data in machine learning, ensuring proper encoding and handling of unseen labels.
Home-page: https://github.com/varunvinodh/Functions/tree/main/Encoder
Author: Varun Vinodh
Author-email: varunvinodh25@gmail.com
License: MIT
Keywords: encoder
Classifier: Development Status :: 5 - Production/Stable
Classifier: Intended Audience :: Science/Research
Classifier: Operating System :: Microsoft :: Windows :: Windows 10
Classifier: License :: OSI Approved :: MIT License
Classifier: Programming Language :: Python :: 3
License-File: LICENCE.txt
